configuration/__init__.py
configuration/backup/__init__.py
configuration/backup/crowd_to_dict.py
configuration/backup/crowd_to_zip_and_reverse.py
configuration/backup/dict_to_xml_and_reverse.py
configuration/backup/xml_to_Chaos.py
configuration/data/__init__.py
configuration/data/datafactory.py
configuration/models/__init__.py
configuration/models/agents.py
configuration/models/crowd.py
configuration/models/initial_agents.py
configuration/models/measures.py
configuration/models/shapes2D.py
configuration/models/shapes3D.py
configuration/utils/__init__.py
configuration/utils/constants.py
configuration/utils/functions.py
configuration/utils/typing_custom.py
lemons_crowd-1.0.1.dist-info/licenses/LICENSE.txt
streamlit_app/__init__.py
streamlit_app/app/__init__.py
streamlit_app/app/app.py
streamlit_app/app/documentation.py
streamlit_app/app/ui.py
streamlit_app/plot/__init__.py
streamlit_app/plot/plot.py
streamlit_app/tabs/__init__.py
streamlit_app/tabs/anthropometry_tab.py
streamlit_app/tabs/crowd_creation_tab.py
streamlit_app/tabs/one_agent_2D.py
streamlit_app/tabs/one_agent_tab.py
streamlit_app/tabs/one_pedestrian_3D.py
streamlit_app/utils/__init__.py
streamlit_app/utils/constants.py
streamlit_app/utils/functions.py
streamlit_app/utils/logging.py
lemons_crowd-1.0.1.dist-info/METADATA
lemons_crowd-1.0.1.dist-info/WHEEL
lemons_crowd-1.0.1.dist-info/top_level.txt
lemons_crowd-1.0.1.dist-info/RECORD
