Metadata-Version: 2.4
Name: lemons-crowd
Version: 1.0.1
Summary: Python wrapper for the LEMONS library to generate anthropometry-based, non-circular pedestrian shapes, visualize crowds, and simulate 2D dynamics.
Author-email: Oscar DUFOUR <oscar.dufour@univ-lyon1.fr>, Maxime STAPELLE <maxime.stapelle@univ-lyon1.fr>, Alexandre NICOLAS <alexandre.nicolas@univ-lyon1.fr>
License-Expression: CECILL-B
Project-URL: Homepage, https://github.com/Crowd-Mechanics/LEMONS
Project-URL: Issues, https://github.com/Crowd-Mechanics/LEMONS/issues
Keywords: crowd generation,crowd dynamics,pedestrian dynamics,anthropometry,mechanical interactions,bideltoid breadth,chest depth,non-circular shapes
Classifier: Operating System :: MacOS
Classifier: Operating System :: POSIX :: Linux
Classifier: Programming Language :: Python :: 3.13
Requires-Python: >=3.13
License-File: LICENSE.txt
Requires-Dist: cmcrameri>=1.9
Requires-Dist: dicttoxml>=1.7.16
Requires-Dist: gprof2dot>=2025.4.14
Requires-Dist: jupyter>=1.1.1
Requires-Dist: kaleido>=1.2.0
Requires-Dist: kivy>=2.3.1
Requires-Dist: matplotlib>=3.10.3
Requires-Dist: numpy>=2.2.6
Requires-Dist: pandas>=2.2.3
Requires-Dist: plotly>=6.1.1
Requires-Dist: pyvista>=0.45.2
Requires-Dist: scipy>=1.15.3
Requires-Dist: shapely>=2.1.1
Requires-Dist: streamlit>=1.45.1
Requires-Dist: streamlit-option-menu>=0.4.0
Requires-Dist: watchdog>=6.0.0
Requires-Dist: xmltodict>=0.14.2
Dynamic: license-file
